maxapi/__init__.py
maxapi/bot.py
maxapi/dispatcher.py
maxapi/loggers.py
maxapi/client/__init__.py
maxapi/client/default.py
maxapi/connection/__init__.py
maxapi/connection/base.py
maxapi/context/__init__.py
maxapi/context/context.py
maxapi/context/state_machine.py
maxapi/enums/__init__.py
maxapi/enums/api_path.py
maxapi/enums/attachment.py
maxapi/enums/button_type.py
maxapi/enums/chat_permission.py
maxapi/enums/chat_status.py
maxapi/enums/chat_type.py
maxapi/enums/http_method.py
maxapi/enums/intent.py
maxapi/enums/message_link_type.py
maxapi/enums/parse_mode.py
maxapi/enums/sender_action.py
maxapi/enums/text_style.py
maxapi/enums/update.py
maxapi/enums/upload_type.py
maxapi/exceptions/__init__.py
maxapi/exceptions/dispatcher.py
maxapi/exceptions/download_file.py
maxapi/exceptions/max.py
maxapi/filters/__init__.py
maxapi/filters/callback_payload.py
maxapi/filters/command.py
maxapi/filters/filter.py
maxapi/filters/handler.py
maxapi/filters/middleware.py
maxapi/methods/__init__.py
maxapi/methods/add_admin_chat.py
maxapi/methods/add_members_chat.py
maxapi/methods/change_info.py
maxapi/methods/delete_bot_from_chat.py
maxapi/methods/delete_chat.py
maxapi/methods/delete_message.py
maxapi/methods/delete_pin_message.py
maxapi/methods/edit_chat.py
maxapi/methods/edit_message.py
maxapi/methods/get_chat_by_id.py
maxapi/methods/get_chat_by_link.py
maxapi/methods/get_chats.py
maxapi/methods/get_list_admin_chat.py
maxapi/methods/get_me.py
maxapi/methods/get_me_from_chat.py
maxapi/methods/get_members_chat.py
maxapi/methods/get_message.py
maxapi/methods/get_messages.py
maxapi/methods/get_pinned_message.py
maxapi/methods/get_subscriptions.py
maxapi/methods/get_updates.py
maxapi/methods/get_upload_url.py
maxapi/methods/get_video.py
maxapi/methods/pin_message.py
maxapi/methods/remove_admin.py
maxapi/methods/remove_member_chat.py
maxapi/methods/send_action.py
maxapi/methods/send_callback.py
maxapi/methods/send_message.py
maxapi/methods/subscribe_webhook.py
maxapi-0.9.12.dist-info/METADATA
maxapi-0.9.12.dist-info/WHEEL
maxapi-0.9.12.dist-info/top_level.txt
maxapi-0.9.12.dist-info/RECORD
