Metadata-Version: 2.4
Name: maxapi
Version: 0.9.12
Summary: Библиотека для разработки чат-ботов с помощью API мессенджера MAX
Author-email: Denis <bestloveapples@gmail.com>
Project-URL: Homepage, https://github.com/love-apples/maxapi
Keywords: max,api,bot
Classifier: Programming Language :: Python :: 3.10
Classifier: Programming Language :: Python :: 3.11
Requires-Python: >=3.10
Requires-Dist: aiohttp>=3.12.14
Requires-Dist: magic_filter>=1.0.0
Requires-Dist: pydantic>=1.8.0
Requires-Dist: aiofiles==24.1.0
Requires-Dist: puremagic==1.30
Provides-Extra: webhook
Requires-Dist: fastapi>=0.68.0; extra == "webhook"
Requires-Dist: uvicorn>=0.15.0; extra == "webhook"
